yc_lockbox/__init__.py
yc_lockbox/_abc.py
yc_lockbox/_adapters.py
yc_lockbox/_auth.py
yc_lockbox/_constants.py
yc_lockbox/_exceptions.py
yc_lockbox/_lockbox.py
yc_lockbox/_models.py
yc_lockbox/_types.py
yc_lockbox-0.2.0.dist-info/LICENSE
yc_lockbox-0.2.0.dist-info/METADATA
yc_lockbox-0.2.0.dist-info/WHEEL
yc_lockbox-0.2.0.dist-info/top_level.txt
yc_lockbox-0.2.0.dist-info/RECORD
