Metadata-Version: 2.1
Name: yc-lockbox
Version: 0.2.0
Summary: Yandex Lockbox client
Home-page: https://github.com/akimrx/python-yc-lockbox
Author: Akim Faskhutdinov
Author-email: akimstrong@yandex.ru
License: MIT
Keywords: yandex,cloud,vault,secrets,lockbox
Platform: osx
Platform: linux
Classifier: License :: OSI Approved :: MIT License
Classifier: Intended Audience :: Information Technology
Classifier: Intended Audience :: System Administrators
Classifier: Intended Audience :: Developers
Classifier: Operating System :: OS Independent
Classifier: Topic :: Software Development :: Libraries :: Python Modules
Classifier: Topic :: Software Development :: Libraries
Classifier: Topic :: Software Development
Classifier: Programming Language :: Python :: 3.10
Classifier: Programming Language :: Python :: 3.11
Classifier: Programming Language :: Python :: 3.12
Classifier: Typing :: Typed
Requires-Python: >=3.10
License-File: LICENSE
Requires-Dist: cryptography >=42.0.0
Requires-Dist: pydantic <3.0.0,>=2.0.0
Requires-Dist: PyJWT <3.0.0,>=2.5.0
Requires-Dist: requests <3.0.0,>=2.30.0
Provides-Extra: aio
Requires-Dist: aiohttp <4.0.0,>=3.9.0 ; extra == 'aio'
